pjsekai/__about__.py
pjsekai/__init__.py
pjsekai/api.py
pjsekai/asset.py
pjsekai/asset_bundle.py
pjsekai/client.py
pjsekai/exceptions.py
pjsekai/live.py
pjsekai/py.typed
pjsekai/utilities.py
pjsekai/bin/darwin/vgmstream/vgmstream-cli
pjsekai/bin/linux/vgmstream/vgmstream-cli
pjsekai/bin/win64/vgmstream/COPYING
pjsekai/bin/win64/vgmstream/README.md
pjsekai/bin/win64/vgmstream/USAGE.md
pjsekai/bin/win64/vgmstream/avcodec-vgmstream-59.dll
pjsekai/bin/win64/vgmstream/avformat-vgmstream-59.dll
pjsekai/bin/win64/vgmstream/avutil-vgmstream-57.dll
pjsekai/bin/win64/vgmstream/libatrac9.dll
pjsekai/bin/win64/vgmstream/libcelt-0061.dll
pjsekai/bin/win64/vgmstream/libcelt-0110.dll
pjsekai/bin/win64/vgmstream/libg719_decode.dll
pjsekai/bin/win64/vgmstream/libmpg123-0.dll
pjsekai/bin/win64/vgmstream/libspeex-1.dll
pjsekai/bin/win64/vgmstream/libvorbis.dll
pjsekai/bin/win64/vgmstream/swresample-vgmstream-4.dll
pjsekai/bin/win64/vgmstream/vgmstream-cli.exe
pjsekai/data/AndroidPlayerSettingConfigTypeTree.json
pjsekai/data/IOSPlayerSettingConfigTypeTree.json
pjsekai/enums/__init__.py
pjsekai/enums/enums.py
pjsekai/enums/information.py
pjsekai/enums/platform.py
pjsekai/enums/ranking.py
pjsekai/enums/tutorial_status.py
pjsekai/enums/unknown.py
pjsekai/enums/user.py
pjsekai/models/__init__.py
pjsekai/models/asset_bundle_info.py
pjsekai/models/game_version.py
pjsekai/models/information.py
pjsekai/models/master_data.py
pjsekai/models/model.py
pjsekai/models/player_setting_config.py
pjsekai/models/ranking.py
pjsekai/models/system_info.py
pjsekai/models/user.py
pypjsekai-0.0.15.dist-info/METADATA
pypjsekai-0.0.15.dist-info/WHEEL
pypjsekai-0.0.15.dist-info/licenses/LICENSE.txt
pypjsekai-0.0.15.dist-info/RECORD
