Metadata-Version: 2.4
Name: pypjsekai
Version: 0.0.15
Summary: Reverse engineered Python client for the mobile rhythm game Project SEKAI COLORFUL STAGE! feat. Hatsune Miku
Project-URL: Documentation, https://github.com/pjsek-ai/pypjsekai#readme
Project-URL: Issues, https://github.com/pjsek-ai/pypjsekai/issues
Project-URL: Source, https://github.com/pjsek-ai/pypjsekai
Author-email: Erik Chan <erikchan002@gmail.com>
License-Expression: MIT
License-File: LICENSE.txt
Classifier: Development Status :: 3 - Alpha
Classifier: Programming Language :: Python
Classifier: Programming Language :: Python :: 3.9
Classifier: Programming Language :: Python :: 3.10
Classifier: Programming Language :: Python :: 3.11
Classifier: Programming Language :: Python :: 3.12
Classifier: Programming Language :: Python :: 3.13
Requires-Python: >=3.9
Requires-Dist: aenum==3.1.16
Requires-Dist: msgpack==1.0.8
Requires-Dist: pycryptodome==3.20.0
Requires-Dist: pydantic==2.7.0
Requires-Dist: pyjwt==2.8.0
Requires-Dist: requests==2.32.3
Provides-Extra: appinfo
Requires-Dist: unitypy==1.20.10; extra == 'appinfo'
Provides-Extra: assetbundle
Requires-Dist: ffmpeg-python==0.2.0; extra == 'assetbundle'
Requires-Dist: python-json-logger~=2.0.2; extra == 'assetbundle'
Requires-Dist: unitypy==1.20.10; extra == 'assetbundle'
Requires-Dist: wannacri==0.3.0; extra == 'assetbundle'
